[
    {
        "youtubeId": "70L60vfGX7w",
        "title": "Video 1"
    },
    {
        "youtubeId": "9JqcOlyK0bA",
        "title": "Video 2"
    },
    {
        "youtubeId": "KtpCD_ZOWI0",
        "title": "Video 3"
    },
    {
        "youtubeId": "43Scx6DNCfE",
        "title": "Video 4"
    },
    {
        "youtubeId": "UoFx8H2nrM8",
        "title": "Video 5"
    },
    {
        "youtubeId": "D4dNO8TI91A",
        "title": "Video 6"
    },
    {
        "youtubeId": "4kEsQAPzzeo",
        "title": "Video 7"
    },
    {
        "youtubeId": "rkoUDeTpZ0I",
        "title": "Video 8"
    },
    {
        "youtubeId": "ytzidAyZ0-4",
        "title": "Video 9"
    },
    {
        "youtubeId": "GUwj1CGN5kw",
        "title": "Video 10"
    },
    {
        "youtubeId": "BxiVXayShJs",
        "title": "Video 11"
    },
    {
        "youtubeId": "FfshhL6KQcs",
        "title": "Video 12"
    },
    {
        "youtubeId": "Ak80MF9pmuY",
        "title": "Video 13"
    },
    {
        "youtubeId": "h3n5zH7u7Pk",
        "title": "Video 14"
    },
    {
        "youtubeId": "u2btfEqh78A",
        "title": "Video 15"
    },
    {
        "youtubeId": "01tKtKEcY18",
        "title": "Video 16"
    },
    {
        "youtubeId": "eBD9eXy7HOY",
        "title": "Video 17"
    },
    {
        "youtubeId": "j8cvid1yOR0",
        "title": "Video 18"
    },
    {
        "youtubeId": "hTypaxZ_g5Q",
        "title": "Video 19"
    },
    {
        "youtubeId": "IWnCc5BpqzI",
        "title": "Video 20"
    },
    {
        "youtubeId": "axrtLN7rFgg",
        "title": "Video 21"
    },
    {
        "youtubeId": "3egQpm3wftw",
        "title": "Video 22"
    },
    {
        "youtubeId": "o7azsXhDCZo",
        "title": "Video 23"
    },
    {
        "youtubeId": "cBR-oXg4E4s",
        "title": "Video 24"
    },
    {
        "youtubeId": "8aDl44NhxFY",
        "title": "Video 25"
    }
  ]
